[
  {
    "id": 1,
    "user_id": 2,
    "amount": 1000,
    "transaction_type": "credit_purchase",
    "description": "Purchased 1000 credits",
    "payment_method": null,
    "payment_status": "completed",
    "payfast_payment_id": null,
    "created_at": null
  },
  {
    "id": 2,
    "user_id": 1,
    "appointment_id": 3,
    "amount": 150,
    "currency": "ZAR",
    "transaction_type": null,
    "description": "Yoco payment for appointment #3",
    "payment_method": "yoco",
    "payment_status": "completed",
    "payfast_payment_id": null,
    "created_at": null
  },
  {
    "id": 3,
    "user_id": 1,
    "appointment_id": 4,
    "amount": 150,
    "currency": "ZAR",
    "transaction_type": null,
    "description": "Yoco payment for appointment #4",
    "payment_method": "yoco",
    "payment_status": "completed",
    "payfast_payment_id": null,
    "created_at": null
  },
  {
    "id": 4,
    "user_id": 2,
    "appointment_id": 5,
    "amount": 150,
    "currency": "ZAR",
    "transaction_type": null,
    "description": "Yoco payment for appointment #5",
    "payment_method": "yoco",
    "payment_status": "completed",
    "payfast_payment_id": null,
    "created_at": null
  },
  {
    "id": 5,
    "user_id": 1,
    "appointment_id": 6,
    "amount": 800,
    "currency": "ZAR",
    "transaction_type": "appointment_payment",
    "description": "Yoco payment for appointment #6",
    "payment_method": "yoco",
    "payment_status": "completed",
    "payfast_payment_id": null,
    "created_at": null
  },
  {
    "id": 6,
    "user_id": 1,
    "appointment_id": 7,
    "amount": 800,
    "currency": "ZAR",
    "transaction_type": "appointment_payment",
    "description": "Yoco payment for appointment #7",
    "payment_method": "yoco",
    "payment_status": "completed",
    "payfast_payment_id": null,
    "created_at": null
  },
  {
    "id": 7,
    "user_id": 1,
    "appointment_id": 8,
    "amount": 800,
    "currency": "ZAR",
    "transaction_type": "appointment_payment",
    "description": "Yoco payment for appointment #8",
    "payment_method": "yoco",
    "payment_status": "completed",
    "payfast_payment_id": null,
    "created_at": null
  },
  {
    "id": 8,
    "user_id": 1,
    "appointment_id": 9,
    "amount": 800,
    "currency": "ZAR",
    "transaction_type": "appointment_payment",
    "description": "Yoco payment for appointment #9",
    "payment_method": "yoco",
    "payment_status": "completed",
    "payfast_payment_id": null,
    "created_at": null
  },
  {
    "id": 9,
    "user_id": 1,
    "appointment_id": 10,
    "amount": 800,
    "currency": "ZAR",
    "transaction_type": "appointment_payment",
    "description": "Yoco payment for appointment #10",
    "payment_method": "yoco",
    "payment_status": "pending",
    "payfast_payment_id": null,
    "created_at": null
  },
  {
    "id": 10,
    "user_id": 1,
    "appointment_id": 11,
    "amount": 800,
    "currency": "ZAR",
    "transaction_type": "appointment_payment",
    "description": "Yoco payment for appointment #11",
    "payment_method": "yoco",
    "payment_status": "pending",
    "payfast_payment_id": null,
    "created_at": null
  },
  {
    "id": 11,
    "user_id": 1,
    "appointment_id": 12,
    "amount": 800,
    "currency": "ZAR",
    "transaction_type": "appointment_payment",
    "description": "Yoco payment for appointment #12",
    "payment_method": "yoco",
    "payment_status": "completed",
    "payfast_payment_id": null,
    "created_at": null
  },
  {
    "id": 12,
    "user_id": 1,
    "appointment_id": 13,
    "amount": 800,
    "currency": "ZAR",
    "transaction_type": "appointment_payment",
    "description": "Yoco payment for appointment #13",
    "payment_method": "yoco",
    "payment_status": "pending",
    "payfast_payment_id": null,
    "created_at": null
  }
]